{
    "external_url": "https://mons.link/mons/g2smm222.png",
    "image": "https://mons.link/mons/g2smm222.png",
    "attributes": {
        "Material": "Clay",
        "Personality": "Wise",
        "Type": "Mystic",
        "Material 2": "Gem",
        "GAN Brilliance": "Fine"
    },
    "name": "Grampuh mowch ",
    "description": "Gen 2 of Super Metal Mons!! A GAN mini figure project. Each of these mons were curated from tens of thousands of generated mini figures and keshi toys. 777 ancient mini sculptures for nobles, art lovers, and avant venture capitalists alike."
}